s2s/__init__.py
s2s-0.0.0.dist-info/LICENSE
s2s-0.0.0.dist-info/METADATA
s2s-0.0.0.dist-info/WHEEL
s2s-0.0.0.dist-info/top_level.txt
s2s-0.0.0.dist-info/RECORD
